<?xml version="1.0" encoding="utf-8"?>
<!DOCTYPE hibernate-mapping PUBLIC "-//Hibernate/Hibernate Mapping DTD 3.0//EN"
                                   "http://hibernate.sourceforge.net/hibernate-mapping-3.0.dtd">
<!-- 
    Mapping file autogenerated by MyEclipse Persistence Tools
-->
<hibernate-mapping>
 <class catalog="project" name="com.sq.model.vo.SqJobTab" table="sq_job_tab">
  <id name="jobId" type="java.lang.String">
   <column length="3" name="job_id"/>
   <generator class="assigned"/>
  </id>
  <property generated="never" lazy="false" name="jobName" type="java.lang.String">
   <column length="50" name="job_name" not-null="true"/>
  </property>
  <property generated="never" lazy="false" name="status" type="java.lang.String">
   <column length="1" name="status" not-null="true"/>
  </property>
  <property generated="never" lazy="false" name="indexNo" type="java.lang.Integer">
   <column name="index_no"/>
  </property>
 </class>
</hibernate-mapping>
